[
    {
        "title": "Do Pal",
        "file": "Audio/Do Pal -Lyrics- English Translation Veer-Zara Sonu Nigam-Lata Mangeshkar Late Madan Mohan .mp3",
        "image": "Thumbnails/Do Pal -Lyrics- English Translation Veer-Zara Sonu Nigam-Lata Mangeshkar Late Madan Mohan _thumbnail.jpg",
        "artist": "Sonu Nigam"
    },
    {
        "title": "Kabhi Alvida Naa Kehna",
        "file": "Audio/Kabhi Alvida Naa Kehna - Bollywood Song Lyrics Translation.mp3",
        "image": "Thumbnails/Kabhi Alvida Naa Kehna - Bollywood Song Lyrics Translation_thumbnail.jpg",
        "artist": "Sonu Nigam"
    },
    {
        "title": "Kal Ho Naa Ho",
        "file": "Audio/Kal Ho Naa Ho -lyrics Sonu Nigam Kal Ho Naa Ho -LYRICS🖤.mp3",
        "image": "Thumbnails/Kal Ho Naa Ho -lyrics Sonu Nigam Kal Ho Naa Ho -LYRICS🖤_thumbnail.jpg",
        "artist": "Sonu Nigam"
    },
    {
        "title": "Kiska Hai Ye Tumko Intezar",
        "file": "Audio/Kiska Hai Ye Tumko Intezar Lyrics - Main Hoon Na -Title Song-.mp3",
        "image": "Thumbnails/Kiska Hai Ye Tumko Intezar Lyrics - Main Hoon Na -Title Song-_thumbnail.jpg",
        "artist": "Sonu Nigam"
    },
    {
        "title": "Main Agar Kahoon",
        "file": "Audio/Main Agar Kahoon Lyrics Shreya Ghoshal Sonu Nigam Shahrukh Khan -Deepika RB Lyrics Lover.mp3",
        "image": "Thumbnails/Main Agar Kahoon Lyrics Shreya Ghoshal Sonu Nigam Shahrukh Khan -Deepika RB Lyrics Lover_thumbnail.jpg",
        "artist": "Sonu Nigam"
    },
    {
        "title": "Mere Haath Mein",
        "file": "Audio/Mere Haath Mein -Lyrics- Fanaa Aamir Khan- Kajol Sonu Nigam- Sunidhi Chauhan.mp3",
        "image": "Thumbnails/Mere Haath Mein -Lyrics- Fanaa Aamir Khan- Kajol Sonu Nigam- Sunidhi Chauhan_thumbnail.jpg",
        "artist": "Sonu Nigam"
    },
    {
        "title": "Sandese Aate Hai",
        "file": "Audio/Sandese Aate Hai -Lyrics- Border Patriotic Songs 15 August Independence Day.mp3",
        "image": "Thumbnails/Sandese Aate Hai -Lyrics- Border Patriotic Songs 15 August Independence Day_thumbnail.jpg",
        "artist": "Sonu Nigam"
    },
    {
        "title": "Sapna Jahan",
        "file": "Audio/Sapna Jahan - Sonu Nigam Slowed - Reverb Lyrics Use Headphones 🎧🎧.mp3",
        "image": "Thumbnails/Sapna Jahan - Sonu Nigam Slowed - Reverb Lyrics Use Headphones 🎧🎧_thumbnail.jpg",
        "artist": "Sonu Nigam"
    },
    {
        "title": "Shukran Allah",
        "file": "Audio/Shukran Allah lyrics Shreya Ghoshal Sonu Nigam Salim-Sulaiman I Kareena Kapoor Saif Ali Khan.mp3",
        "image": "Thumbnails/Shukran Allah lyrics Shreya Ghoshal Sonu Nigam Salim-Sulaiman I Kareena Kapoor Saif Ali Khan_thumbnail.jpg",
        "artist": "Sonu Nigam"
    },
    {
        "title": "Abhi Mujh Mein Kahin",
        "file": "Audio/Sonu Nigam- Ajay-Atul - Abhi Mujh Mein Kahin -Lyrics-.mp3",
        "image": "Thumbnails/Sonu Nigam- Ajay-Atul - Abhi Mujh Mein Kahin -Lyrics-_thumbnail.jpg",
        "artist": "Sonu Nigam"
    },
    {
        "title": "Tumse Milke Dil Ka Jo Haal",
        "file": "Audio/Tumse milke dilka jo haal -lyrics- lyrics tube.mp3",
        "image": "Thumbnails/Tumse milke dilka jo haal -lyrics- lyrics tube_thumbnail.jpg",
        "artist": "Sonu Nigam"
    }
]